aig/__init__.py
aig/example.py
aig-0.1.dist-info/METADATA
aig-0.1.dist-info/WHEEL
aig-0.1.dist-info/licenses/LICENSE
aig-0.1.dist-info/RECORD
