Metadata-Version: 2.4
Name: aig
Version: 0.1
Summary: A simple example package
Project-URL: Homepage, https://github.com/nicky/aig
Project-URL: Bug Tracker, https://github.com/nicky/aig/issues
Author-email: Nicky <nicky@example.com>
License-File: LICENSE
Classifier: License :: OSI Approved :: MIT License
Classifier: Operating System :: OS Independent
Classifier: Programming Language :: Python :: 3
Requires-Python: >=3.8
